battlib/__init__.py
battlib/__init__.pyi
battlib/battery.py
battlib/battery.pyi
battlib/cc.py
battlib/cc.pyi
battlib/ekf.py
battlib/ekf.pyi
battlib/ocv.py
battlib/ocv.pyi
battlib/py.typed
battlib/utilities.py
battlib/utilities.pyi
battlib-0.0.0.dev2.dist-info/LICENSE
battlib-0.0.0.dev2.dist-info/METADATA
battlib-0.0.0.dev2.dist-info/WHEEL
battlib-0.0.0.dev2.dist-info/top_level.txt
battlib-0.0.0.dev2.dist-info/RECORD
