Metadata-Version: 2.2
Name: battlib
Version: 0.0.0.dev2
Summary: A library for battery SOC calculation
Home-page: https://github.com/blueskysolarracing/battlib
Author: Blue Sky Solar Racing
Author-email: blueskysolar@studentorg.utoronto.ca
License: MIT
Project-URL: Documentation, https://battlib.readthedocs.io/en/latest/
Project-URL: Source, https://github.com/blueskysolarracing/battlib
Project-URL: Tracker, https://github.com/blueskysolarracing/battlib/issues
Keywords: python
Classifier: Development Status :: 5 - Production/Stable
Classifier: Intended Audience :: Developers
Classifier: Intended Audience :: Education
Classifier: Topic :: Education
Classifier: Topic :: Scientific/Engineering
Classifier: License :: OSI Approved :: MIT License
Classifier: Operating System :: OS Independent
Classifier: Programming Language :: Python
Classifier: Programming Language :: Python :: 3
Classifier: Programming Language :: Python :: 3 :: Only
Classifier: Programming Language :: Python :: 3.11
Classifier: Programming Language :: Python :: 3.12
Requires-Python: >=3.11
License-File: LICENSE
Requires-Dist: filterpy<2,>=1.4.5
Requires-Dist: numpy<3,>=2.2.2
Dynamic: author
Dynamic: author-email
Dynamic: classifier
Dynamic: description
Dynamic: description-content-type
Dynamic: home-page
Dynamic: keywords
Dynamic: license
Dynamic: project-url
Dynamic: requires-dist
Dynamic: requires-python
Dynamic: summary
